{
  "dashboard": {
    "description": "",
    "eventDisplaySettings": {
      "enabled": false,
      "queryParams": {
        "alertStatuses": [],
        "categories": [],
        "filter": "",
        "severities": [],
        "teamScope": false
      }
    },
    "layout": [
      {
        "h": 5,
        "panelId": 1,
        "w": 8,
        "x": 0,
        "y": 0
      },
      {
        "h": 5,
        "panelId": 2,
        "w": 12,
        "x": 12,
        "y": 5
      },
      {
        "h": 5,
        "panelId": 3,
        "w": 12,
        "x": 0,
        "y": 5
      },
      {
        "h": 5,
        "panelId": 4,
        "w": 12,
        "x": 0,
        "y": 10
      },
      {
        "h": 5,
        "panelId": 5,
        "w": 12,
        "x": 12,
        "y": 10
      },
      {
        "h": 5,
        "panelId": 6,
        "w": 12,
        "x": 12,
        "y": 15
      },
      {
        "h": 5,
        "panelId": 7,
        "w": 12,
        "x": 0,
        "y": 15
      },
      {
        "h": 5,
        "panelId": 8,
        "w": 8,
        "x": 16,
        "y": 20
      },
      {
        "h": 5,
        "panelId": 9,
        "w": 8,
        "x": 0,
        "y": 20
      },
      {
        "h": 5,
        "panelId": 10,
        "w": 8,
        "x": 8,
        "y": 20
      },
      {
        "h": 5,
        "panelId": 11,
        "w": 8,
        "x": 16,
        "y": 0
      },
      {
        "h": 5,
        "panelId": 12,
        "w": 8,
        "x": 8,
        "y": 0
      }
    ],
    "name": "Postgresql - Instance Health",
    "panels": [
      {
        "advancedQueries": [
          {
            "displayInfo": {
              "displayName": "",
              "timeSeriesDisplayNameTemplate": "",
              "type": "lines"
            },
            "enabled": true,
            "format": {
              "decimals": null,
              "displayFormat": "auto",
              "inputFormat": "1",
              "unit": "number",
              "yAxis": "auto"
            },
            "query": "avg((pg_up{} * on (container_id, host_mac) group_left(cluster,namespace,pod) sysdig_container_info{cluster=~$cluster,namespace=~$namespace}) * on (pod) group_left(owner_name,owner_kind) kube_pod_owner{owner_kind=\"ReplicaSet\",cluster=~$cluster,namespace=~$namespace,owner_name=~$replicaSet})"
          }
        ],
        "description": "",
        "id": 1,
        "name": "UP",
        "numberThresholds": {
          "base": {
            "displayText": "DOWN",
            "severity": "high"
          },
          "values": [
            {
              "displayText": "OK",
              "inputFormat": "1",
              "severity": "ok",
              "value": 0.0
            }
          ]
        },
        "type": "advancedNumber"
      },
      {
        "advancedQueries": [
          {
            "displayInfo": {
              "displayName": " ",
              "timeSeriesDisplayNameTemplate": "Rate - {{owner_name}} - {{cluster}}",
              "type": "lines"
            },
            "enabled": true,
            "format": {
              "decimals": null,
              "displayFormat": "auto",
              "inputFormat": "0-100",
              "unit": "%",
              "yAxis": "auto"
            },
            "query": "(100 * \nsum by (container_id,host_mac) (rate(pg_stat_archiver_failed_count{}[$__interval])) / \nsum by (container_id,host_mac) (rate(pg_stat_archiver_archived_count{}[$__interval]) + rate(pg_stat_archiver_failed_count{}[$__interval]))) \n* on (container_id, host_mac) group_left(cluster,namespace,pod) sysdig_container_info{cluster=~$cluster,namespace=~$namespace} * on (pod) group_left(owner_name,owner_kind) kube_pod_owner{owner_kind=\"ReplicaSet\",cluster=~$cluster,namespace=~$namespace,owner_name=~$replicaSet}"
          }
        ],
        "axesConfiguration": {
          "bottom": {
            "enabled": true
          },
          "left": {
            "decimals": null,
            "displayFormat": "auto",
            "displayName": null,
            "enabled": true,
            "maxInputFormat": "0-100",
            "maxValue": null,
            "minInputFormat": "0-100",
            "minValue": null,
            "scale": "linear",
            "unit": "auto"
          },
          "right": {
            "decimals": null,
            "displayFormat": "auto",
            "displayName": null,
            "enabled": true,
            "maxInputFormat": "1",
            "maxValue": null,
            "minInputFormat": "1",
            "minValue": null,
            "scale": "linear",
            "unit": "auto"
          }
        },
        "description": "",
        "id": 2,
        "legendConfiguration": {
          "enabled": true,
          "layout": "inline",
          "position": "bottom",
          "showCurrent": true
        },
        "name": "WAL Files Archive Error Rate",
        "type": "advancedTimechart"
      },
      {
        "advancedQueries": [
          {
            "displayInfo": {
              "displayName": " ",
              "timeSeriesDisplayNameTemplate": "requested - {{owner_name}} - {{cluster}}",
              "type": "lines"
            },
            "enabled": true,
            "format": {
              "decimals": null,
              "displayFormat": "auto",
              "inputFormat": "1",
              "unit": "number",
              "yAxis": "auto"
            },
            "query": "(rate(pg_stat_bgwriter_checkpoints_req{}[$__interval]) * on (container_id, host_mac) group_left(cluster,namespace,pod) sysdig_container_info{cluster=~$cluster,namespace=~$namespace}) * on (pod) group_left(owner_name,owner_kind) kube_pod_owner{owner_kind=\"ReplicaSet\",cluster=~$cluster,namespace=~$namespace,owner_name=~$replicaSet}"
          },
          {
            "displayInfo": {
              "displayName": " ",
              "timeSeriesDisplayNameTemplate": "scheduled - {{owner_name}} - {{cluster}}",
              "type": "lines"
            },
            "enabled": true,
            "format": {
              "decimals": null,
              "displayFormat": "auto",
              "inputFormat": "1",
              "unit": "number",
              "yAxis": "auto"
            },
            "query": "(rate(pg_stat_bgwriter_checkpoints_timed{}[$__interval]) * on (container_id, host_mac) group_left(cluster,namespace,pod) sysdig_container_info{cluster=~$cluster,namespace=~$namespace}) * on (pod) group_left(owner_name,owner_kind) kube_pod_owner{owner_kind=\"ReplicaSet\",cluster=~$cluster,namespace=~$namespace,owner_name=~$replicaSet}"
          }
        ],
        "axesConfiguration": {
          "bottom": {
            "enabled": true
          },
          "left": {
            "decimals": null,
            "displayFormat": "auto",
            "displayName": null,
            "enabled": true,
            "maxInputFormat": "1",
            "maxValue": null,
            "minInputFormat": "1",
            "minValue": 0.0,
            "scale": "linear",
            "unit": "auto"
          },
          "right": {
            "decimals": null,
            "displayFormat": "auto",
            "displayName": null,
            "enabled": true,
            "maxInputFormat": "1",
            "maxValue": null,
            "minInputFormat": "1",
            "minValue": null,
            "scale": "linear",
            "unit": "auto"
          }
        },
        "description": "",
        "id": 3,
        "legendConfiguration": {
          "enabled": true,
          "layout": "inline",
          "position": "bottom",
          "showCurrent": true
        },
        "name": "Scheduled vs Requested Checkpoints",
        "type": "advancedTimechart"
      },
      {
        "advancedQueries": [
          {
            "displayInfo": {
              "displayName": " ",
              "timeSeriesDisplayNameTemplate": "sync to disk - {{owner_name}} - {{cluster}}",
              "type": "lines"
            },
            "enabled": true,
            "format": {
              "decimals": null,
              "displayFormat": "auto",
              "inputFormat": "ms",
              "unit": "relativeTime",
              "yAxis": "auto"
            },
            "query": "(rate(pg_stat_bgwriter_checkpoint_sync_time{}[$__interval]) * on (container_id, host_mac) group_left(cluster,namespace,pod) sysdig_container_info{cluster=~$cluster,namespace=~$namespace}) * on (pod) group_left(owner_name,owner_kind) kube_pod_owner{owner_kind=\"ReplicaSet\",cluster=~$cluster,namespace=~$namespace,owner_name=~$replicaSet}"
          },
          {
            "displayInfo": {
              "displayName": " ",
              "timeSeriesDisplayNameTemplate": "write to disk - {{owner_name}} - {{cluster}}",
              "type": "lines"
            },
            "enabled": true,
            "format": {
              "decimals": null,
              "displayFormat": "auto",
              "inputFormat": "ms",
              "unit": "relativeTime",
              "yAxis": "auto"
            },
            "query": "(rate(pg_stat_bgwriter_checkpoint_write_time{}[$__interval]) * on (container_id, host_mac) group_left(cluster,namespace,pod) sysdig_container_info{cluster=~$cluster,namespace=~$namespace}) * on (pod) group_left(owner_name,owner_kind) kube_pod_owner{owner_kind=\"ReplicaSet\",cluster=~$cluster,namespace=~$namespace,owner_name=~$replicaSet}"
          }
        ],
        "axesConfiguration": {
          "bottom": {
            "enabled": true
          },
          "left": {
            "decimals": null,
            "displayFormat": "auto",
            "displayName": null,
            "enabled": true,
            "maxInputFormat": "ns",
            "maxValue": null,
            "minInputFormat": "ns",
            "minValue": null,
            "scale": "linear",
            "unit": "auto"
          },
          "right": {
            "decimals": null,
            "displayFormat": "auto",
            "displayName": null,
            "enabled": true,
            "maxInputFormat": "1",
            "maxValue": null,
            "minInputFormat": "1",
            "minValue": null,
            "scale": "linear",
            "unit": "auto"
          }
        },
        "description": "",
        "id": 4,
        "legendConfiguration": {
          "enabled": true,
          "layout": "inline",
          "position": "bottom",
          "showCurrent": true
        },
        "name": "Checkpoint time",
        "type": "advancedTimechart"
      },
      {
        "advancedQueries": [
          {
            "displayInfo": {
              "displayName": " ",
              "timeSeriesDisplayNameTemplate": "rate - {{owner_name}} - {{cluster}}",
              "type": "lines"
            },
            "enabled": true,
            "format": {
              "decimals": null,
              "displayFormat": "auto",
              "inputFormat": "0-100",
              "unit": "%",
              "yAxis": "auto"
            },
            "query": "(100 * sum by (container_id,host_mac) (rate(pg_stat_bgwriter_buffers_backend{}[$__interval])) /  \nsum by (container_id,host_mac) (rate(pg_stat_bgwriter_buffers_backend{}[$__interval]) + rate(pg_stat_bgwriter_buffers_checkpoint{}[$__interval]) + rate(pg_stat_bgwriter_buffers_clean{}[$__interval])) \n* on (container_id,host_mac) group_left(cluster,namespace,pod) sysdig_container_info{cluster=~$cluster,namespace=~$namespace}) * on (pod) group_left(owner_name,owner_kind) kube_pod_owner{owner_kind=\"ReplicaSet\",cluster=~$cluster,namespace=~$namespace,owner_name=~$replicaSet}\n"
          }
        ],
        "axesConfiguration": {
          "bottom": {
            "enabled": true
          },
          "left": {
            "decimals": null,
            "displayFormat": "auto",
            "displayName": null,
            "enabled": true,
            "maxInputFormat": "0-100",
            "maxValue": null,
            "minInputFormat": "0-100",
            "minValue": null,
            "scale": "linear",
            "unit": "auto"
          },
          "right": {
            "decimals": null,
            "displayFormat": "auto",
            "displayName": null,
            "enabled": true,
            "maxInputFormat": "1",
            "maxValue": null,
            "minInputFormat": "1",
            "minValue": null,
            "scale": "linear",
            "unit": "auto"
          }
        },
        "description": "",
        "id": 5,
        "legendConfiguration": {
          "enabled": true,
          "layout": "inline",
          "position": "bottom",
          "showCurrent": true
        },
        "name": "Backend Buffer Write Rate",
        "type": "advancedTimechart"
      },
      {
        "advancedQueries": [
          {
            "displayInfo": {
              "displayName": " ",
              "timeSeriesDisplayNameTemplate": "stops - {{owner_name}} - {{cluster}}",
              "type": "lines"
            },
            "enabled": true,
            "format": {
              "decimals": null,
              "displayFormat": "auto",
              "inputFormat": "1",
              "unit": "number",
              "yAxis": "auto"
            },
            "query": "(rate(pg_stat_bgwriter_maxwritten_clean{}[$__interval])\n* on (container_id, host_mac) group_left(cluster,namespace,pod) sysdig_container_info{cluster=~$cluster,namespace=~$namespace}) * on (pod) group_left(owner_name,owner_kind) kube_pod_owner{owner_kind=\"ReplicaSet\",cluster=~$cluster,namespace=~$namespace,owner_name=~$replicaSet}"
          }
        ],
        "axesConfiguration": {
          "bottom": {
            "enabled": true
          },
          "left": {
            "decimals": null,
            "displayFormat": "auto",
            "displayName": null,
            "enabled": true,
            "maxInputFormat": "1",
            "maxValue": null,
            "minInputFormat": "1",
            "minValue": null,
            "scale": "linear",
            "unit": "auto"
          },
          "right": {
            "decimals": null,
            "displayFormat": "auto",
            "displayName": null,
            "enabled": true,
            "maxInputFormat": "1",
            "maxValue": null,
            "minInputFormat": "1",
            "minValue": null,
            "scale": "linear",
            "unit": "auto"
          }
        },
        "description": "",
        "id": 6,
        "legendConfiguration": {
          "enabled": true,
          "layout": "inline",
          "position": "bottom",
          "showCurrent": true
        },
        "name": "Background Writer Stops for Max Write Buffers",
        "type": "advancedTimechart"
      },
      {
        "advancedQueries": [
          {
            "displayInfo": {
              "displayName": " ",
              "timeSeriesDisplayNameTemplate": "buffers - {{owner_name}} - {{cluster}}",
              "type": "lines"
            },
            "enabled": true,
            "format": {
              "decimals": null,
              "displayFormat": "auto",
              "inputFormat": "1",
              "unit": "number",
              "yAxis": "auto"
            },
            "query": "(rate(pg_stat_bgwriter_buffers_alloc{}[$__interval]) \n* on (container_id, host_mac) group_left(cluster,namespace,pod) sysdig_container_info{cluster=~$cluster,namespace=~$namespace}) * on (pod) group_left(owner_name,owner_kind) kube_pod_owner{owner_kind=\"ReplicaSet\",cluster=~$cluster,namespace=~$namespace,owner_name=~$replicaSet}\n"
          }
        ],
        "axesConfiguration": {
          "bottom": {
            "enabled": true
          },
          "left": {
            "decimals": null,
            "displayFormat": "auto",
            "displayName": null,
            "enabled": true,
            "maxInputFormat": "1",
            "maxValue": null,
            "minInputFormat": "1",
            "minValue": 0.0,
            "scale": "linear",
            "unit": "auto"
          },
          "right": {
            "decimals": null,
            "displayFormat": "auto",
            "displayName": null,
            "enabled": true,
            "maxInputFormat": "1",
            "maxValue": null,
            "minInputFormat": "1",
            "minValue": null,
            "scale": "linear",
            "unit": "auto"
          }
        },
        "description": "",
        "id": 7,
        "legendConfiguration": {
          "enabled": true,
          "layout": "inline",
          "position": "bottom",
          "showCurrent": true
        },
        "name": "Buffers Allocated",
        "type": "advancedTimechart"
      },
      {
        "advancedQueries": [
          {
            "displayInfo": {
              "displayName": " ",
              "timeSeriesDisplayNameTemplate": "{{datname}} - {{owner_name}} - {{cluster}}",
              "type": "lines"
            },
            "enabled": true,
            "format": {
              "decimals": null,
              "displayFormat": "auto",
              "inputFormat": "s",
              "unit": "relativeTime",
              "yAxis": "auto"
            },
            "query": "(avg(rate(pg_stat_activity_max_tx_duration{datname!~'template.*'}[$__interval])) by (datname,container_id, host_mac)\n* on (container_id, host_mac) group_left(cluster,namespace,pod) sysdig_container_info{cluster=~$cluster,namespace=~$namespace}) * on (pod) group_left(owner_name,owner_kind) kube_pod_owner{owner_kind=\"ReplicaSet\",cluster=~$cluster,namespace=~$namespace,owner_name=~$replicaSet}"
          }
        ],
        "axesConfiguration": {
          "bottom": {
            "enabled": true
          },
          "left": {
            "decimals": null,
            "displayFormat": "auto",
            "displayName": null,
            "enabled": true,
            "maxInputFormat": "ns",
            "maxValue": null,
            "minInputFormat": "ns",
            "minValue": null,
            "scale": "linear",
            "unit": "auto"
          },
          "right": {
            "decimals": null,
            "displayFormat": "auto",
            "displayName": null,
            "enabled": true,
            "maxInputFormat": "1",
            "maxValue": null,
            "minInputFormat": "1",
            "minValue": null,
            "scale": "linear",
            "unit": "auto"
          }
        },
        "description": "",
        "id": 8,
        "legendConfiguration": {
          "enabled": true,
          "layout": "inline",
          "position": "bottom",
          "showCurrent": true
        },
        "name": "Max Transaction Time by DB",
        "type": "advancedTimechart"
      },
      {
        "advancedQueries": [
          {
            "displayInfo": {
              "displayName": " ",
              "timeSeriesDisplayNameTemplate": "rate - {{owner_name}} - {{cluster}}",
              "type": "lines"
            },
            "enabled": true,
            "format": {
              "decimals": null,
              "displayFormat": "auto",
              "inputFormat": "0-100",
              "unit": "%",
              "yAxis": "auto"
            },
            "query": "(100 * sum(pg_stat_activity_count{}) by (container_id,host_mac)  / ((sum(pg_settings_max_connections{}) by (container_id,host_mac)) - sum(pg_settings_superuser_reserved_connections{}) by (container_id,host_mac))\n* on (container_id, host_mac) group_left(cluster,namespace,pod) sysdig_container_info{cluster=~$cluster,namespace=~$namespace}) * on (pod) group_left(owner_name,owner_kind) kube_pod_owner{owner_kind=\"ReplicaSet\",cluster=~$cluster,namespace=~$namespace,owner_name=~$replicaSet}"
          }
        ],
        "axesConfiguration": {
          "bottom": {
            "enabled": true
          },
          "left": {
            "decimals": null,
            "displayFormat": "auto",
            "displayName": null,
            "enabled": true,
            "maxInputFormat": "0-100",
            "maxValue": null,
            "minInputFormat": "0-100",
            "minValue": null,
            "scale": "linear",
            "unit": "auto"
          },
          "right": {
            "decimals": null,
            "displayFormat": "auto",
            "displayName": null,
            "enabled": true,
            "maxInputFormat": "1",
            "maxValue": null,
            "minInputFormat": "1",
            "minValue": null,
            "scale": "linear",
            "unit": "auto"
          }
        },
        "description": "",
        "id": 9,
        "legendConfiguration": {
          "enabled": true,
          "layout": "inline",
          "position": "bottom",
          "showCurrent": true
        },
        "name": "Connections Usage Percentage",
        "type": "advancedTimechart"
      },
      {
        "advancedQueries": [
          {
            "displayInfo": {
              "displayName": " ",
              "timeSeriesDisplayNameTemplate": "connections - {{owner_name}} - {{cluster}}",
              "type": "lines"
            },
            "enabled": true,
            "format": {
              "decimals": null,
              "displayFormat": "auto",
              "inputFormat": "1",
              "unit": "number",
              "yAxis": "auto"
            },
            "query": "(((sum(pg_settings_max_connections{}) by (container_id,host_mac) - sum(pg_settings_superuser_reserved_connections{}) by (container_id,host_mac)) - sum(pg_stat_activity_count{}) by (container_id,host_mac) )\n* on (container_id, host_mac) group_left(cluster,namespace,pod) sysdig_container_info{cluster=~$cluster,namespace=~$namespace}) * on (pod) group_left(owner_name,owner_kind) kube_pod_owner{owner_kind=\"ReplicaSet\",cluster=~$cluster,namespace=~$namespace,owner_name=~$replicaSet}\n"
          }
        ],
        "axesConfiguration": {
          "bottom": {
            "enabled": true
          },
          "left": {
            "decimals": null,
            "displayFormat": "auto",
            "displayName": null,
            "enabled": true,
            "maxInputFormat": "1",
            "maxValue": null,
            "minInputFormat": "1",
            "minValue": 0.0,
            "scale": "linear",
            "unit": "auto"
          },
          "right": {
            "decimals": null,
            "displayFormat": "auto",
            "displayName": null,
            "enabled": true,
            "maxInputFormat": "1",
            "maxValue": null,
            "minInputFormat": "1",
            "minValue": null,
            "scale": "linear",
            "unit": "auto"
          }
        },
        "description": "",
        "id": 10,
        "legendConfiguration": {
          "enabled": true,
          "layout": "inline",
          "position": "bottom",
          "showCurrent": true
        },
        "name": "Available Connections",
        "type": "advancedTimechart"
      },
      {
        "advancedQueries": [
          {
            "displayInfo": {
              "displayName": " ",
              "timeSeriesDisplayNameTemplate": "{{datname}} - {{owner_name}} - {{cluster}}",
              "type": "lines"
            },
            "enabled": true,
            "format": {
              "decimals": null,
              "displayFormat": "auto",
              "inputFormat": "B",
              "unit": "byte",
              "yAxis": "auto"
            },
            "query": "((pg_database_size_bytes{} * on (container_id, host_mac) group_left(cluster,namespace,pod) sysdig_container_info{cluster=~$cluster,namespace=~$namespace}) * on (pod) group_left(owner_name,owner_kind) kube_pod_owner{owner_kind=\"ReplicaSet\",cluster=~$cluster,namespace=~$namespace,owner_name=~$replicaSet})"
          }
        ],
        "axesConfiguration": {
          "bottom": {
            "enabled": true
          },
          "left": {
            "decimals": null,
            "displayFormat": "auto",
            "displayName": null,
            "enabled": true,
            "maxInputFormat": "B",
            "maxValue": null,
            "minInputFormat": "B",
            "minValue": 0.0,
            "scale": "linear",
            "unit": "auto"
          },
          "right": {
            "decimals": null,
            "displayFormat": "auto",
            "displayName": null,
            "enabled": true,
            "maxInputFormat": "1",
            "maxValue": null,
            "minInputFormat": "1",
            "minValue": null,
            "scale": "linear",
            "unit": "auto"
          }
        },
        "description": "",
        "id": 11,
        "legendConfiguration": {
          "enabled": true,
          "layout": "inline",
          "position": "bottom",
          "showCurrent": true
        },
        "name": "DBs Size",
        "type": "advancedTimechart"
      },
      {
        "advancedQueries": [
          {
            "displayInfo": {
              "displayName": "",
              "timeSeriesDisplayNameTemplate": "",
              "type": "lines"
            },
            "enabled": true,
            "format": {
              "decimals": null,
              "displayFormat": "auto",
              "inputFormat": "s",
              "unit": "relativeTime",
              "yAxis": "auto"
            },
            "query": "time() - avg((pg_postmaster_start_time_seconds{} * on (container_id,host_mac) group_left(cluster,namespace,pod) sysdig_container_info{cluster=~$cluster,namespace=~$namespace}) * on (pod) group_left(owner_name,owner_kind) kube_pod_owner{owner_kind=\"ReplicaSet\",cluster=~$cluster,namespace=~$namespace})\n"
          }
        ],
        "description": "",
        "id": 12,
        "name": "Postmaster Uptime",
        "numberThresholds": {
          "base": {
            "displayText": "",
            "severity": "high"
          },
          "values": [
            {
              "displayText": "",
              "inputFormat": "s",
              "severity": "ok",
              "value": 3600.0
            },
            {
              "displayText": "",
              "inputFormat": "s",
              "severity": "low",
              "value": 1800.0
            }
          ]
        },
        "type": "advancedNumber"
      }
    ],
    "schema": 3,
    "scopeExpressionList": [
      {
        "descriptor": {
          "aggregationForGroup": "none",
          "canFilter": true,
          "canGroupBy": true,
          "canMonitor": false,
          "category": "kubernetes",
          "createdAt": 1593615677662,
          "customerId": 25008,
          "deferred": false,
          "documentId": "25008--6139949314852700299",
          "documentTimestamp": 1593615677662,
          "documentType": "metric",
          "experimental": false,
          "firstSeen": 1583235308502,
          "generatedFrom": "com.draios.model.metrics.kubernetes.KubernetesName",
          "generator": {
            "aggregationForGroup": "none",
            "aggregations": [
              "concat",
              "distinct",
              "count"
            ],
            "avg": false,
            "canCalculate": false,
            "canFilter": true,
            "canGroupBy": true,
            "canMonitor": false,
            "category": "kubernetes",
            "concat": false,
            "context": [
              "container"
            ],
            "count": false,
            "countDistinct": false,
            "deferred": false,
            "experimental": false,
            "firstSeen": 1583235308502,
            "groupAggregations": [
              "concat",
              "distinct",
              "count"
            ],
            "groupBy": [],
            "heuristic": false,
            "hidden": false,
            "id": "kubernetes.cluster.name",
            "identity": false,
            "label": true,
            "lastSeen": 1593614229731,
            "max": false,
            "metricType": "none",
            "min": false,
            "namespaces": [
              "kubernetes.cluster"
            ],
            "rateOfChange": false,
            "scale": 1.0,
            "scopes": [],
            "sum": false,
            "timeAggregations": [
              "concat",
              "distinct",
              "count"
            ],
            "timeAvg": false,
            "type": "string"
          },
          "groupAggregations": [
            "concat",
            "distinct",
            "count"
          ],
          "heuristic": false,
          "hidden": false,
          "id": "kubernetes.cluster.name",
          "identity": false,
          "lastSeen": 1593614229731,
          "metricType": "tag",
          "namespaces": [
            "kubernetes.cluster"
          ],
          "routingInfo": {
            "customerId": 25008,
            "routing": "25008"
          },
          "scale": 1.0,
          "scopes": [],
          "segment": false,
          "segmentations": [],
          "timeAggregations": [
            "concat",
            "distinct",
            "count"
          ],
          "type": "string"
        },
        "displayName": "cluster",
        "isVariable": true,
        "operand": "kubernetes.cluster.name",
        "operator": "in",
        "value": [],
        "variable": true
      },
      {
        "descriptor": {
          "aggregationForGroup": "none",
          "canFilter": true,
          "canGroupBy": true,
          "canMonitor": false,
          "category": "kubernetes",
          "createdAt": 1593615677663,
          "customerId": 25008,
          "deferred": false,
          "documentId": "25008--7083949535721519842",
          "documentTimestamp": 1593615677663,
          "documentType": "metric",
          "experimental": false,
          "firstSeen": 1583235308502,
          "generatedFrom": "com.draios.model.metrics.kubernetes.KubernetesName",
          "generator": {
            "aggregationForGroup": "none",
            "aggregations": [
              "concat",
              "distinct",
              "count"
            ],
            "avg": false,
            "canCalculate": false,
            "canFilter": true,
            "canGroupBy": true,
            "canMonitor": false,
            "category": "kubernetes",
            "concat": false,
            "context": [
              "container"
            ],
            "count": false,
            "countDistinct": false,
            "deferred": false,
            "experimental": false,
            "firstSeen": 1583235308502,
            "groupAggregations": [
              "concat",
              "distinct",
              "count"
            ],
            "groupBy": [],
            "heuristic": false,
            "hidden": false,
            "id": "kubernetes.namespace.name",
            "identity": false,
            "label": true,
            "lastSeen": 1593614709967,
            "max": false,
            "metricType": "none",
            "min": false,
            "namespaces": [
              "kubernetes.namespace"
            ],
            "rateOfChange": false,
            "scale": 1.0,
            "scopes": [],
            "sum": false,
            "timeAggregations": [
              "concat",
              "distinct",
              "count"
            ],
            "timeAvg": false,
            "type": "string"
          },
          "groupAggregations": [
            "concat",
            "distinct",
            "count"
          ],
          "heuristic": false,
          "hidden": false,
          "id": "kubernetes.namespace.name",
          "identity": false,
          "lastSeen": 1593614709967,
          "metricType": "tag",
          "namespaces": [
            "kubernetes.namespace"
          ],
          "routingInfo": {
            "customerId": 25008,
            "routing": "25008"
          },
          "scale": 1.0,
          "scopes": [],
          "segment": false,
          "segmentations": [],
          "timeAggregations": [
            "concat",
            "distinct",
            "count"
          ],
          "type": "string"
        },
        "displayName": "namespace",
        "isVariable": true,
        "operand": "kubernetes.namespace.name",
        "operator": "in",
        "value": [],
        "variable": true
      },
      {
        "descriptor": {
          "aggregationForGroup": "none",
          "canFilter": true,
          "canGroupBy": true,
          "canMonitor": false,
          "category": "kubernetes",
          "createdAt": 1593615677663,
          "customerId": 25008,
          "deferred": false,
          "documentId": "25008-9123524798813735958",
          "documentTimestamp": 1593615677663,
          "documentType": "metric",
          "experimental": false,
          "firstSeen": 1583235308502,
          "generatedFrom": "com.draios.model.metrics.kubernetes.KubernetesName",
          "generator": {
            "aggregationForGroup": "none",
            "aggregations": [
              "concat",
              "distinct",
              "count"
            ],
            "avg": false,
            "canCalculate": false,
            "canFilter": true,
            "canGroupBy": true,
            "canMonitor": false,
            "category": "kubernetes",
            "concat": false,
            "context": [
              "container"
            ],
            "count": false,
            "countDistinct": false,
            "deferred": false,
            "experimental": false,
            "firstSeen": 1583235308502,
            "groupAggregations": [
              "concat",
              "distinct",
              "count"
            ],
            "groupBy": [],
            "heuristic": false,
            "hidden": false,
            "id": "kubernetes.replicaSet.name",
            "identity": false,
            "label": true,
            "lastSeen": 1593613392685,
            "max": false,
            "metricType": "none",
            "min": false,
            "namespaces": [
              "kubernetes.replicaSet"
            ],
            "rateOfChange": false,
            "scale": 1.0,
            "scopes": [],
            "sum": false,
            "timeAggregations": [
              "concat",
              "distinct",
              "count"
            ],
            "timeAvg": false,
            "type": "string"
          },
          "groupAggregations": [
            "concat",
            "distinct",
            "count"
          ],
          "heuristic": false,
          "hidden": false,
          "id": "kubernetes.replicaSet.name",
          "identity": false,
          "lastSeen": 1593613392685,
          "metricType": "tag",
          "namespaces": [
            "kubernetes.replicaSet"
          ],
          "routingInfo": {
            "customerId": 25008,
            "routing": "25008"
          },
          "scale": 1.0,
          "scopes": [],
          "segment": false,
          "segmentations": [],
          "timeAggregations": [
            "concat",
            "distinct",
            "count"
          ],
          "type": "string"
        },
        "displayName": "replicaSet",
        "isVariable": true,
        "operand": "kubernetes.replicaSet.name",
        "operator": "in",
        "value": [],
        "variable": true
      }
    ]
  }
}